flclient/__init__.py
flclient/cli.py
flclient/flclient.py
flclient-0.0.1.dist-info/METADATA
flclient-0.0.1.dist-info/WHEEL
flclient-0.0.1.dist-info/licenses/LICENSE
flclient-0.0.1.dist-info/RECORD
