Metadata-Version: 2.4
Name: flclient
Version: 0.0.1
Summary: Python client library for the FitLayout REST API
Project-URL: Repository, https://github.com/FitLayout/fitlayout-python-client
Author-email: Radek Burget <burgetr@fit.vut.cz>
License:                   GNU LESSER GENERAL PUBLIC LICENSE
License-File: LICENSE
Keywords: api,client,fitlayout,rest
Classifier: Development Status :: 3 - Alpha
Classifier: Intended Audience :: Developers
Classifier: License :: OSI Approved :: GNU Lesser General Public License v3 or later (LGPLv3+)
Classifier: Operating System :: OS Independent
Classifier: Programming Language :: Python :: 3
Classifier: Topic :: Software Development :: Libraries :: Python Modules
Requires-Python: >=3.10
Requires-Dist: rdflib>=7.1.1
Requires-Dist: requests>=2.32.3
